{"teams":[{"mid":"21281","tid":"12","tname":"Bridgeport","vault":"19.6125","bars":"29.3000","beam":"19.3500","floor":"29.6000","tscore":"97.8625","year":"2017","home":"A","lead":0},{"mid":"21283","tid":"35","tname":"Lindenwood","vault":"9.9375","bars":"19.6000","beam":"28.5500","floor":"28.4250","tscore":"86.5125","year":"2017","home":"A","lead":11.3499999999999996447286321199499070644378662109375},{"mid":"21285","tid":"63","tname":"Texas Woman's","vault":"29.4250","bars":"28.9000","beam":"19.4750","floor":"1.0000","tscore":"78.8000","year":"2017","home":"A","lead":19.0625},{"mid":"21277","tid":"57","tname":"Seattle Pacific","vault":"9.7875","bars":"9.8250","beam":"19.4000","floor":"29.1250","tscore":"68.1375","year":"2017","home":"H","lead":29.72500000000000142108547152020037174224853515625},{"mid":"21282","tid":"18","tname":"Cornell","vault":"9.8000","bars":"19.7500","beam":"19.6500","floor":"9.4250","tscore":"58.6250","year":"2017","home":"A","lead":39.2374999999999971578290569595992565155029296875},{"mid":"21284","tid":"82","tname":"Yale","vault":"19.4250","bars":"0.0000","beam":"9.8250","floor":"28.5500","tscore":"57.8000","year":"2017","home":"A","lead":40.0625},{"mid":"21280","tid":"1","tname":"Air Force","vault":"18.9125","bars":"0.0000","beam":"9.8000","floor":"19.5750","tscore":"48.2875","year":"2017","home":"A","lead":49.5750000000000028421709430404007434844970703125},{"mid":"21288","tid":"50","tname":"Pennsylvania","vault":"0.0000","bars":"0.0000","beam":"9.8000","floor":"19.6250","tscore":"29.4250","year":"2017","home":"A","lead":68.4375},{"mid":"21279","tid":"72","tname":"West Chester","vault":"9.7500","bars":"9.7750","beam":"9.8250","floor":"0.0000","tscore":"29.3500","year":"2017","home":"A","lead":68.5125000000000028421709430404007434844970703125},{"mid":"21286","tid":"16","tname":"Centenary College","vault":"0.0000","bars":"0.0000","beam":"9.8750","floor":"0.0000","tscore":"9.8750","year":"2017","home":"A","lead":87.9874999999999971578290569595992565155029296875},{"mid":"21278","tid":"14","tname":"Brown","vault":"0.0000","bars":"9.8500","beam":"0.0000","floor":"0.0000","tscore":"9.8500","year":"2017","home":"A","lead":88.0125000000000028421709430404007434844970703125},{"mid":"21287","tid":"58","tname":"Southern Conn.","vault":"0.0000","bars":"0.0000","beam":"9.7500","floor":"0.0000","tscore":"9.7500","year":"2017","home":"A","lead":88.1124999999999971578290569595992565155029296875}],"scores":[[{"gid":"24338","first_name":"Kelly ","last_name":"Aycock","vault":null,"bars":"9.7000","beam":null,"floor":null,"all_around":null,"team_name":"Bridgeport","team_id":"12","yr":"2017","vt_url":null,"ub_url":null,"bb_url":null,"fx_url":null},{"gid":"23755","first_name":"Carol","last_name":"Chiles","vault":null,"bars":null,"beam":"9.5750","floor":null,"all_around":null,"team_name":"Bridgeport","team_id":"12","yr":"2017","vt_url":null,"ub_url":null,"bb_url":null,"fx_url":null},{"gid":"23756","first_name":"Brianna","last_name":"Comport","vault":null,"bars":null,"beam":null,"floor":"9.9000","all_around":null,"team_name":"Bridgeport","team_id":"12","yr":"2017","vt_url":null,"ub_url":null,"bb_url":null,"fx_url":null},{"gid":"24339","first_name":"Maritza","last_name":"Futch ","vault":null,"bars":"9.7500","beam":null,"floor":null,"all_around":null,"team_name":"Bridgeport","team_id":"12","yr":"2017","vt_url":null,"ub_url":null,"bb_url":null,"fx_url":null},{"gid":"24337","first_name":"Thomara","last_name":"Powell-Brown","vault":null,"bars":"9.8500","beam":null,"floor":null,"all_around":null,"team_name":"Bridgeport","team_id":"12","yr":"2017","vt_url":null,"ub_url":null,"bb_url":null,"fx_url":null},{"gid":"24937","first_name":"Maya","last_name":"Reimers","vault":null,"bars":null,"beam":"9.7750","floor":"9.8250","all_around":null,"team_name":"Bridgeport","team_id":"12","yr":"2017","vt_url":null,"ub_url":null,"bb_url":null,"fx_url":null},{"gid":"23774","first_name":"Kimberly","last_name":"Stewart","vault":"9.8625","bars":null,"beam":null,"floor":"9.8750","all_around":null,"team_name":"Bridgeport","team_id":"12","yr":"2017","vt_url":null,"ub_url":null,"bb_url":null,"fx_url":null},{"gid":"24939","first_name":"Nina","last_name":"Whittaker","vault":"9.7500","bars":null,"beam":null,"floor":null,"all_around":null,"team_name":"Bridgeport","team_id":"12","yr":"2017","vt_url":null,"ub_url":null,"bb_url":null,"fx_url":null}],[{"gid":"24072","first_name":"Andavea","last_name":"Alexander","vault":null,"bars":null,"beam":"9.7750","floor":"9.6750","all_around":null,"team_name":"Lindenwood","team_id":"35","yr":"2017","vt_url":null,"ub_url":null,"bb_url":null,"fx_url":null},{"gid":"24780","first_name":"Breanna","last_name":"Franklin","vault":null,"bars":null,"beam":null,"floor":"9.8000","all_around":null,"team_name":"Lindenwood","team_id":"35","yr":"2017","vt_url":null,"ub_url":null,"bb_url":null,"fx_url":null},{"gid":"23805","first_name":"Aubree","last_name":"Horn","vault":null,"bars":null,"beam":"8.9750","floor":null,"all_around":null,"team_name":"Lindenwood","team_id":"35","yr":"2017","vt_url":null,"ub_url":null,"bb_url":null,"fx_url":null},{"gid":"24073","first_name":"Katey ","last_name":"Oswalt","vault":null,"bars":null,"beam":null,"floor":"8.9500","all_around":null,"team_name":"Lindenwood","team_id":"35","yr":"2017","vt_url":null,"ub_url":null,"bb_url":null,"fx_url":null},{"gid":"23811","first_name":"Hannah","last_name":"Rector","vault":null,"bars":"9.8000","beam":null,"floor":null,"all_around":null,"team_name":"Lindenwood","team_id":"35","yr":"2017","vt_url":null,"ub_url":null,"bb_url":null,"fx_url":null},{"gid":"23812","first_name":"Kierstin","last_name":"Sokolowski","vault":"9.9375","bars":"9.8000","beam":"9.8000","floor":null,"all_around":null,"team_name":"Lindenwood","team_id":"35","yr":"2017","vt_url":null,"ub_url":null,"bb_url":null,"fx_url":null}],[{"gid":"24092","first_name":"Jenna","last_name":"Cashmore","vault":null,"bars":"9.3250","beam":null,"floor":null,"all_around":null,"team_name":"Texas Woman's","team_id":"63","yr":"2017","vt_url":null,"ub_url":null,"bb_url":null,"fx_url":null},{"gid":"24094","first_name":"Megan ","last_name":"Gentry","vault":"9.7250","bars":null,"beam":null,"floor":null,"all_around":null,"team_name":"Texas Woman's","team_id":"63","yr":"2017","vt_url":null,"ub_url":null,"bb_url":null,"fx_url":null},{"gid":"24680","first_name":"Schyler","last_name":"Jones","vault":"9.8250","bars":"9.7750","beam":null,"floor":null,"all_around":null,"team_name":"Texas Woman's","team_id":"63","yr":"2017","vt_url":null,"ub_url":null,"bb_url":null,"fx_url":null},{"gid":"23100","first_name":"Alyssa","last_name":"Kelly","vault":null,"bars":"9.8000","beam":"9.7750","floor":null,"all_around":null,"team_name":"Texas Woman's","team_id":"63","yr":"2017","vt_url":null,"ub_url":null,"bb_url":null,"fx_url":null},{"gid":"23103","first_name":"Mallory","last_name":"Moredock","vault":"9.8750","bars":null,"beam":null,"floor":null,"all_around":null,"team_name":"Texas Woman's","team_id":"63","yr":"2017","vt_url":null,"ub_url":null,"bb_url":null,"fx_url":null},{"gid":"24682","first_name":"Bria","last_name":"Northrop","vault":null,"bars":null,"beam":null,"floor":"1.0000","all_around":null,"team_name":"Texas Woman's","team_id":"63","yr":"2017","vt_url":null,"ub_url":null,"bb_url":null,"fx_url":null},{"gid":"23106","first_name":"Katie","last_name":"Simpson","vault":null,"bars":null,"beam":"9.7000","floor":null,"all_around":null,"team_name":"Texas Woman's","team_id":"63","yr":"2017","vt_url":null,"ub_url":null,"bb_url":null,"fx_url":null}],[{"gid":"23873","first_name":"Breanna","last_name":"Beltran","vault":null,"bars":null,"beam":"9.6250","floor":null,"all_around":null,"team_name":"Seattle Pacific","team_id":"57","yr":"2017","vt_url":null,"ub_url":null,"bb_url":null,"fx_url":null},{"gid":"24928","first_name":"Darian","last_name":"Burns","vault":"9.7875","bars":null,"beam":"9.7750","floor":"9.9000","all_around":null,"team_name":"Seattle Pacific","team_id":"57","yr":"2017","vt_url":null,"ub_url":null,"bb_url":null,"fx_url":null},{"gid":"23877","first_name":"Lauren","last_name":"Glover","vault":null,"bars":null,"beam":null,"floor":"9.5750","all_around":null,"team_name":"Seattle Pacific","team_id":"57","yr":"2017","vt_url":null,"ub_url":null,"bb_url":null,"fx_url":null},{"gid":"23878","first_name":"Ariana","last_name":"Harger","vault":null,"bars":null,"beam":null,"floor":"9.6500","all_around":null,"team_name":"Seattle Pacific","team_id":"57","yr":"2017","vt_url":null,"ub_url":null,"bb_url":null,"fx_url":null},{"gid":"23879","first_name":"Kristi","last_name":"Hayashida","vault":null,"bars":"9.8250","beam":null,"floor":null,"all_around":null,"team_name":"Seattle Pacific","team_id":"57","yr":"2017","vt_url":null,"ub_url":null,"bb_url":null,"fx_url":null}],[{"gid":"23950","first_name":"Lyanda","last_name":"Dudley","vault":"9.8000","bars":null,"beam":null,"floor":"9.4250","all_around":null,"team_name":"Cornell","team_id":"18","yr":"2017","vt_url":null,"ub_url":null,"bb_url":null,"fx_url":null},{"gid":"22655","first_name":"Joy","last_name":"Gage","vault":null,"bars":"9.8500","beam":null,"floor":null,"all_around":null,"team_name":"Cornell","team_id":"18","yr":"2017","vt_url":null,"ub_url":null,"bb_url":null,"fx_url":null},{"gid":"23951","first_name":"Kaitlin","last_name":"Green","vault":null,"bars":"9.9000","beam":"9.9000","floor":null,"all_around":null,"team_name":"Cornell","team_id":"18","yr":"2017","vt_url":null,"ub_url":null,"bb_url":null,"fx_url":null},{"gid":"22671","first_name":"Lauren","last_name":"Wong","vault":null,"bars":null,"beam":"9.7500","floor":null,"all_around":null,"team_name":"Cornell","team_id":"18","yr":"2017","vt_url":null,"ub_url":null,"bb_url":null,"fx_url":null}],[{"gid":"23987","first_name":"Kiarra","last_name":"Alleyne","vault":null,"bars":null,"beam":null,"floor":"9.1500","all_around":null,"team_name":"Yale","team_id":"82","yr":"2017","vt_url":null,"ub_url":null,"bb_url":null,"fx_url":null},{"gid":"23427","first_name":"Anella","last_name":"Anderson","vault":null,"bars":null,"beam":null,"floor":"9.7750","all_around":null,"team_name":"Yale","team_id":"82","yr":"2017","vt_url":null,"ub_url":null,"bb_url":null,"fx_url":null},{"gid":"24543","first_name":"Jade","last_name":"Buford","vault":null,"bars":null,"beam":null,"floor":"9.6250","all_around":null,"team_name":"Yale","team_id":"82","yr":"2017","vt_url":null,"ub_url":null,"bb_url":null,"fx_url":null},{"gid":"24546","first_name":"Rebecca","last_name":"Chong","vault":"9.8000","bars":null,"beam":null,"floor":null,"all_around":null,"team_name":"Yale","team_id":"82","yr":"2017","vt_url":null,"ub_url":null,"bb_url":null,"fx_url":null},{"gid":"24542","first_name":"Anna","last_name":"Jennings","vault":"9.6250","bars":null,"beam":null,"floor":null,"all_around":null,"team_name":"Yale","team_id":"82","yr":"2017","vt_url":null,"ub_url":null,"bb_url":null,"fx_url":null},{"gid":"23434","first_name":"Megan","last_name":"Ryan","vault":null,"bars":null,"beam":"9.8250","floor":null,"all_around":null,"team_name":"Yale","team_id":"82","yr":"2017","vt_url":null,"ub_url":null,"bb_url":null,"fx_url":null}],[{"gid":"22425","first_name":"Casey","last_name":"Bell","vault":null,"bars":null,"beam":null,"floor":"9.8250","all_around":null,"team_name":"Air Force","team_id":"1","yr":"2017","vt_url":null,"ub_url":null,"bb_url":null,"fx_url":null},{"gid":"24452","first_name":"Anna","last_name":"Salamone","vault":"9.2125","bars":null,"beam":"9.8000","floor":null,"all_around":null,"team_name":"Air Force","team_id":"1","yr":"2017","vt_url":null,"ub_url":null,"bb_url":null,"fx_url":null},{"gid":"22441","first_name":"Kara","last_name":"Witgen","vault":"9.7000","bars":null,"beam":null,"floor":"9.7500","all_around":null,"team_name":"Air Force","team_id":"1","yr":"2017","vt_url":null,"ub_url":null,"bb_url":null,"fx_url":null}],[{"gid":"22989","first_name":"Rachel","last_name":"Graham","vault":null,"bars":null,"beam":"9.8000","floor":null,"all_around":null,"team_name":"Pennsylvania","team_id":"50","yr":"2017","vt_url":null,"ub_url":null,"bb_url":null,"fx_url":null},{"gid":"22992","first_name":"Kyra","last_name":"Levi","vault":null,"bars":null,"beam":null,"floor":"9.8000","all_around":null,"team_name":"Pennsylvania","team_id":"50","yr":"2017","vt_url":null,"ub_url":null,"bb_url":null,"fx_url":null},{"gid":"24328","first_name":"Nicole","last_name":"Swirbalus","vault":null,"bars":null,"beam":null,"floor":"9.8250","all_around":null,"team_name":"Pennsylvania","team_id":"50","yr":"2017","vt_url":null,"ub_url":null,"bb_url":null,"fx_url":null}],[{"gid":"23655","first_name":"Majesta","last_name":"Valentine","vault":"9.7500","bars":"9.7750","beam":"9.8250","floor":null,"all_around":null,"team_name":"West Chester","team_id":"72","yr":"2017","vt_url":null,"ub_url":null,"bb_url":null,"fx_url":null}],[{"gid":"23242","first_name":"Ashley","last_name":"White","vault":null,"bars":null,"beam":"9.8750","floor":null,"all_around":null,"team_name":"Centenary College","team_id":"16","yr":"2017","vt_url":null,"ub_url":null,"bb_url":null,"fx_url":null}],[{"gid":"22627","first_name":"Anya","last_name":"Olson","vault":null,"bars":"9.8500","beam":null,"floor":null,"all_around":null,"team_name":"Brown","team_id":"14","yr":"2017","vt_url":null,"ub_url":null,"bb_url":null,"fx_url":null}],[{"gid":"23022","first_name":"Kathleen","last_name":"Aberger","vault":null,"bars":null,"beam":"9.7500","floor":null,"all_around":null,"team_name":"Southern Conn.","team_id":"58","yr":"2017","vt_url":null,"ub_url":null,"bb_url":null,"fx_url":null}]],"vault":[{"tname":"Lindenwood","tid":"35","fname":"Kierstin","lname":"Sokolowski","gid":"23812","score":9.9375,"url":null,"place":1},{"tname":"Texas Woman's","tid":"63","fname":"Mallory","lname":"Moredock","gid":"23103","score":9.875,"url":null,"place":2},{"tname":"Bridgeport","tid":"12","fname":"Kimberly","lname":"Stewart","gid":"23774","score":9.862500000000000710542735760100185871124267578125,"url":null,"place":3},{"tname":"Texas Woman's","tid":"63","fname":"Schyler","lname":"Jones","gid":"24680","score":9.824999999999999289457264239899814128875732421875,"url":null,"place":4},{"tname":"Cornell","tid":"18","fname":"Lyanda","lname":"Dudley","gid":"23950","score":9.800000000000000710542735760100185871124267578125,"url":null,"place":5},{"tname":"Yale","tid":"82","fname":"Rebecca","lname":"Chong","gid":"24546","score":9.800000000000000710542735760100185871124267578125,"url":null,"place":5},{"tname":"Seattle Pacific","tid":"57","fname":"Darian","lname":"Burns","gid":"24928","score":9.7874999999999996447286321199499070644378662109375,"url":null,"place":7},{"tname":"Bridgeport","tid":"12","fname":"Nina","lname":"Whittaker","gid":"24939","score":9.75,"url":null,"place":8},{"tname":"West Chester","tid":"72","fname":"Majesta","lname":"Valentine","gid":"23655","score":9.75,"url":null,"place":8},{"tname":"Texas Woman's","tid":"63","fname":"Megan ","lname":"Gentry","gid":"24094","score":9.7249999999999996447286321199499070644378662109375,"url":null,"place":10},{"tname":"Air Force","tid":"1","fname":"Kara","lname":"Witgen","gid":"22441","score":9.699999999999999289457264239899814128875732421875,"url":null,"place":11},{"tname":"Yale","tid":"82","fname":"Anna","lname":"Jennings","gid":"24542","score":9.625,"url":null,"place":12},{"tname":"Air Force","tid":"1","fname":"Anna","lname":"Salamone","gid":"24452","score":9.2125000000000003552713678800500929355621337890625,"url":null,"place":13}],"bars":[{"tname":"Cornell","tid":"18","fname":"Kaitlin","lname":"Green","gid":"23951","score":9.9000000000000003552713678800500929355621337890625,"url":null,"place":1},{"tname":"Bridgeport","tid":"12","fname":"Thomara","lname":"Powell-Brown","gid":"24337","score":9.8499999999999996447286321199499070644378662109375,"url":null,"place":2},{"tname":"Brown","tid":"14","fname":"Anya","lname":"Olson","gid":"22627","score":9.8499999999999996447286321199499070644378662109375,"url":null,"place":2},{"tname":"Cornell","tid":"18","fname":"Joy","lname":"Gage","gid":"22655","score":9.8499999999999996447286321199499070644378662109375,"url":null,"place":2},{"tname":"Seattle Pacific","tid":"57","fname":"Kristi","lname":"Hayashida","gid":"23879","score":9.824999999999999289457264239899814128875732421875,"url":null,"place":5},{"tname":"Lindenwood","tid":"35","fname":"Hannah","lname":"Rector","gid":"23811","score":9.800000000000000710542735760100185871124267578125,"url":null,"place":6},{"tname":"Lindenwood","tid":"35","fname":"Kierstin","lname":"Sokolowski","gid":"23812","score":9.800000000000000710542735760100185871124267578125,"url":null,"place":6},{"tname":"Texas Woman's","tid":"63","fname":"Alyssa","lname":"Kelly","gid":"23100","score":9.800000000000000710542735760100185871124267578125,"url":null,"place":6},{"tname":"Texas Woman's","tid":"63","fname":"Schyler","lname":"Jones","gid":"24680","score":9.7750000000000003552713678800500929355621337890625,"url":null,"place":9},{"tname":"West Chester","tid":"72","fname":"Majesta","lname":"Valentine","gid":"23655","score":9.7750000000000003552713678800500929355621337890625,"url":null,"place":9},{"tname":"Bridgeport","tid":"12","fname":"Maritza","lname":"Futch ","gid":"24339","score":9.75,"url":null,"place":11},{"tname":"Bridgeport","tid":"12","fname":"Kelly ","lname":"Aycock","gid":"24338","score":9.699999999999999289457264239899814128875732421875,"url":null,"place":12},{"tname":"Texas Woman's","tid":"63","fname":"Jenna","lname":"Cashmore","gid":"24092","score":9.324999999999999289457264239899814128875732421875,"url":null,"place":13}],"beam":[{"tname":"Cornell","tid":"18","fname":"Kaitlin","lname":"Green","gid":"23951","score":9.9000000000000003552713678800500929355621337890625,"url":null,"place":1},{"tname":"Centenary College","tid":"16","fname":"Ashley","lname":"White","gid":"23242","score":9.875,"url":null,"place":2},{"tname":"West Chester","tid":"72","fname":"Majesta","lname":"Valentine","gid":"23655","score":9.824999999999999289457264239899814128875732421875,"url":null,"place":3},{"tname":"Yale","tid":"82","fname":"Megan","lname":"Ryan","gid":"23434","score":9.824999999999999289457264239899814128875732421875,"url":null,"place":3},{"tname":"Air Force","tid":"1","fname":"Anna","lname":"Salamone","gid":"24452","score":9.800000000000000710542735760100185871124267578125,"url":null,"place":5},{"tname":"Lindenwood","tid":"35","fname":"Kierstin","lname":"Sokolowski","gid":"23812","score":9.800000000000000710542735760100185871124267578125,"url":null,"place":5},{"tname":"Pennsylvania","tid":"50","fname":"Rachel","lname":"Graham","gid":"22989","score":9.800000000000000710542735760100185871124267578125,"url":null,"place":5},{"tname":"Bridgeport","tid":"12","fname":"Maya","lname":"Reimers","gid":"24937","score":9.7750000000000003552713678800500929355621337890625,"url":null,"place":8},{"tname":"Lindenwood","tid":"35","fname":"Andavea","lname":"Alexander","gid":"24072","score":9.7750000000000003552713678800500929355621337890625,"url":null,"place":8},{"tname":"Seattle Pacific","tid":"57","fname":"Darian","lname":"Burns","gid":"24928","score":9.7750000000000003552713678800500929355621337890625,"url":null,"place":8},{"tname":"Texas Woman's","tid":"63","fname":"Alyssa","lname":"Kelly","gid":"23100","score":9.7750000000000003552713678800500929355621337890625,"url":null,"place":8},{"tname":"Cornell","tid":"18","fname":"Lauren","lname":"Wong","gid":"22671","score":9.75,"url":null,"place":12},{"tname":"Southern Conn.","tid":"58","fname":"Kathleen","lname":"Aberger","gid":"23022","score":9.75,"url":null,"place":12},{"tname":"Texas Woman's","tid":"63","fname":"Katie","lname":"Simpson","gid":"23106","score":9.699999999999999289457264239899814128875732421875,"url":null,"place":14},{"tname":"Seattle Pacific","tid":"57","fname":"Breanna","lname":"Beltran","gid":"23873","score":9.625,"url":null,"place":15},{"tname":"Bridgeport","tid":"12","fname":"Carol","lname":"Chiles","gid":"23755","score":9.574999999999999289457264239899814128875732421875,"url":null,"place":16},{"tname":"Lindenwood","tid":"35","fname":"Aubree","lname":"Horn","gid":"23805","score":8.9749999999999996447286321199499070644378662109375,"url":null,"place":17}],"floor":[{"tname":"Bridgeport","tid":"12","fname":"Brianna","lname":"Comport","gid":"23756","score":9.9000000000000003552713678800500929355621337890625,"url":null,"place":1},{"tname":"Seattle Pacific","tid":"57","fname":"Darian","lname":"Burns","gid":"24928","score":9.9000000000000003552713678800500929355621337890625,"url":null,"place":1},{"tname":"Bridgeport","tid":"12","fname":"Kimberly","lname":"Stewart","gid":"23774","score":9.875,"url":null,"place":3},{"tname":"Air Force","tid":"1","fname":"Casey","lname":"Bell","gid":"22425","score":9.824999999999999289457264239899814128875732421875,"url":null,"place":4},{"tname":"Bridgeport","tid":"12","fname":"Maya","lname":"Reimers","gid":"24937","score":9.824999999999999289457264239899814128875732421875,"url":null,"place":4},{"tname":"Pennsylvania","tid":"50","fname":"Nicole","lname":"Swirbalus","gid":"24328","score":9.824999999999999289457264239899814128875732421875,"url":null,"place":4},{"tname":"Lindenwood","tid":"35","fname":"Breanna","lname":"Franklin","gid":"24780","score":9.800000000000000710542735760100185871124267578125,"url":null,"place":7},{"tname":"Pennsylvania","tid":"50","fname":"Kyra","lname":"Levi","gid":"22992","score":9.800000000000000710542735760100185871124267578125,"url":null,"place":7},{"tname":"Yale","tid":"82","fname":"Anella","lname":"Anderson","gid":"23427","score":9.7750000000000003552713678800500929355621337890625,"url":null,"place":9},{"tname":"Air Force","tid":"1","fname":"Kara","lname":"Witgen","gid":"22441","score":9.75,"url":null,"place":10},{"tname":"Lindenwood","tid":"35","fname":"Andavea","lname":"Alexander","gid":"24072","score":9.675000000000000710542735760100185871124267578125,"url":null,"place":11},{"tname":"Seattle Pacific","tid":"57","fname":"Ariana","lname":"Harger","gid":"23878","score":9.6500000000000003552713678800500929355621337890625,"url":null,"place":12},{"tname":"Yale","tid":"82","fname":"Jade","lname":"Buford","gid":"24543","score":9.625,"url":null,"place":13},{"tname":"Seattle Pacific","tid":"57","fname":"Lauren","lname":"Glover","gid":"23877","score":9.574999999999999289457264239899814128875732421875,"url":null,"place":14},{"tname":"Cornell","tid":"18","fname":"Lyanda","lname":"Dudley","gid":"23950","score":9.425000000000000710542735760100185871124267578125,"url":null,"place":15},{"tname":"Yale","tid":"82","fname":"Kiarra","lname":"Alleyne","gid":"23987","score":9.1500000000000003552713678800500929355621337890625,"url":null,"place":16},{"tname":"Lindenwood","tid":"35","fname":"Katey ","lname":"Oswalt","gid":"24073","score":8.949999999999999289457264239899814128875732421875,"url":null,"place":17},{"tname":"Texas Woman's","tid":"63","fname":"Bria","lname":"Northrop","gid":"24682","score":1,"url":null,"place":18}],"aa":[],"info":{"meet_desc":"USAG Championships Individual Finals","host":"Seattle Pacific","date":"Apr-09-2017","attendance":"0","live":false},"scoresheets":[]}