{"teams":[{"mid":"21407","tid":"3","tname":"Alaska","vault":"47.2750","bars":"46.7500","beam":"48.3500","floor":"46.4500","tscore":"188.8250","year":"2018","home":"H","lead":0},{"mid":"21612","tid":"19","tname":"Cortland State","vault":"46.4000","bars":"44.5500","beam":"46.9000","floor":"44.8250","tscore":"182.6750","year":"2018","home":"A","lead":6.1500000000000003552713678800500929355621337890625}],"scores":[[{"gid":"23967","first_name":"Kierra ","last_name":"Abraham","vault":"9.5250","bars":"9.1500","beam":null,"floor":null,"all_around":null,"team_name":"Alaska","team_id":"3","yr":"2018","vt_url":null,"ub_url":null,"bb_url":null,"fx_url":null},{"gid":"22463","first_name":"Kendra","last_name":"Daniels","vault":"9.4500","bars":null,"beam":"9.2750","floor":null,"all_around":null,"team_name":"Alaska","team_id":"3","yr":"2018","vt_url":null,"ub_url":null,"bb_url":null,"fx_url":null},{"gid":"25140","first_name":"Isabelle","last_name":"Fox","vault":"9.3500","bars":"9.6000","beam":"9.7250","floor":"9.7000","all_around":"38.3750","team_name":"Alaska","team_id":"3","yr":"2018","vt_url":null,"ub_url":null,"bb_url":null,"fx_url":null},{"gid":"24503","first_name":"Kennedy ","last_name":"Green","vault":"9.4250","bars":"8.6500","beam":null,"floor":"9.5000","all_around":null,"team_name":"Alaska","team_id":"3","yr":"2018","vt_url":null,"ub_url":null,"bb_url":null,"fx_url":null},{"gid":"23970","first_name":"Kaylin","last_name":"Mancari","vault":"9.5000","bars":null,"beam":"9.6250","floor":"9.6750","all_around":null,"team_name":"Alaska","team_id":"3","yr":"2018","vt_url":null,"ub_url":null,"bb_url":null,"fx_url":null},{"gid":"24508","first_name":"Mackenzie","last_name":"Miller","vault":"9.3750","bars":"9.6000","beam":"9.4500","floor":null,"all_around":null,"team_name":"Alaska","team_id":"3","yr":"2018","vt_url":null,"ub_url":null,"bb_url":null,"fx_url":null},{"gid":"25141","first_name":"Hope","last_name":"Nelson","vault":null,"bars":"9.7500","beam":"9.8000","floor":"8.6750","all_around":null,"team_name":"Alaska","team_id":"3","yr":"2018","vt_url":null,"ub_url":null,"bb_url":null,"fx_url":null},{"gid":"25142","first_name":"Michaela","last_name":"Phillips","vault":null,"bars":null,"beam":"9.7500","floor":"8.9000","all_around":null,"team_name":"Alaska","team_id":"3","yr":"2018","vt_url":null,"ub_url":null,"bb_url":null,"fx_url":null}],[{"gid":"29777","first_name":"Samantha","last_name":"Betz","vault":null,"bars":null,"beam":null,"floor":"9.1250","all_around":null,"team_name":"Cortland State","team_id":"19","yr":"2018","vt_url":null,"ub_url":null,"bb_url":null,"fx_url":null},{"gid":"24891","first_name":"Mia ","last_name":"Dimartino","vault":null,"bars":"8.8250","beam":null,"floor":null,"all_around":null,"team_name":"Cortland State","team_id":"19","yr":"2018","vt_url":null,"ub_url":null,"bb_url":null,"fx_url":null},{"gid":"24437","first_name":"Rachel","last_name":"Filipski","vault":"9.5500","bars":null,"beam":null,"floor":"7.4000","all_around":null,"team_name":"Cortland State","team_id":"19","yr":"2018","vt_url":null,"ub_url":null,"bb_url":null,"fx_url":null},{"gid":"29774","first_name":"Julie","last_name":"Giardina","vault":null,"bars":null,"beam":"9.1250","floor":"8.6750","all_around":null,"team_name":"Cortland State","team_id":"19","yr":"2018","vt_url":null,"ub_url":null,"bb_url":null,"fx_url":null},{"gid":"23783","first_name":"Bailey","last_name":"Gildemeyer","vault":"9.1000","bars":null,"beam":"9.4500","floor":null,"all_around":null,"team_name":"Cortland State","team_id":"19","yr":"2018","vt_url":null,"ub_url":null,"bb_url":null,"fx_url":null},{"gid":"24893","first_name":"Sidney","last_name":"McConnell","vault":"9.3750","bars":"9.0000","beam":null,"floor":null,"all_around":null,"team_name":"Cortland State","team_id":"19","yr":"2018","vt_url":null,"ub_url":null,"bb_url":null,"fx_url":null},{"gid":"24894","first_name":"Genna","last_name":"Orlik","vault":null,"bars":null,"beam":"8.5500","floor":null,"all_around":null,"team_name":"Cortland State","team_id":"19","yr":"2018","vt_url":null,"ub_url":null,"bb_url":null,"fx_url":null},{"gid":"23790","first_name":"McKenna","last_name":"Passalacqua","vault":"8.7250","bars":null,"beam":"9.6750","floor":null,"all_around":null,"team_name":"Cortland State","team_id":"19","yr":"2018","vt_url":null,"ub_url":null,"bb_url":null,"fx_url":null},{"gid":"24441","first_name":"Lindsay","last_name":"Riggs","vault":null,"bars":"9.0500","beam":null,"floor":null,"all_around":null,"team_name":"Cortland State","team_id":"19","yr":"2018","vt_url":null,"ub_url":null,"bb_url":null,"fx_url":null},{"gid":"24890","first_name":"Ashley","last_name":"Scarantino","vault":null,"bars":"7.5000","beam":null,"floor":null,"all_around":null,"team_name":"Cortland State","team_id":"19","yr":"2018","vt_url":null,"ub_url":null,"bb_url":null,"fx_url":null},{"gid":"29768","first_name":"Emma","last_name":"Schulz","vault":"8.9750","bars":null,"beam":"9.8000","floor":"9.5000","all_around":null,"team_name":"Cortland State","team_id":"19","yr":"2018","vt_url":null,"ub_url":null,"bb_url":null,"fx_url":null},{"gid":"29776","first_name":"Emily","last_name":"Speciale","vault":null,"bars":"8.6250","beam":null,"floor":null,"all_around":null,"team_name":"Cortland State","team_id":"19","yr":"2018","vt_url":null,"ub_url":null,"bb_url":null,"fx_url":null},{"gid":"24438","first_name":"Lily","last_name":"Szafranski","vault":"9.4000","bars":null,"beam":null,"floor":"8.2750","all_around":null,"team_name":"Cortland State","team_id":"19","yr":"2018","vt_url":null,"ub_url":null,"bb_url":null,"fx_url":null},{"gid":"23795","first_name":"Arianna","last_name":"Turso","vault":null,"bars":"9.0500","beam":"8.8500","floor":"9.2500","all_around":null,"team_name":"Cortland State","team_id":"19","yr":"2018","vt_url":null,"ub_url":null,"bb_url":null,"fx_url":null}]],"vault":[{"tname":"Cortland State","tid":"19","fname":"Rachel","lname":"Filipski","gid":"24437","score":9.550000000000000710542735760100185871124267578125,"url":null,"place":1},{"tname":"Alaska","tid":"3","fname":"Kierra ","lname":"Abraham","gid":"23967","score":9.5250000000000003552713678800500929355621337890625,"url":null,"place":2},{"tname":"Alaska","tid":"3","fname":"Kaylin","lname":"Mancari","gid":"23970","score":9.5,"url":null,"place":3},{"tname":"Alaska","tid":"3","fname":"Kendra","lname":"Daniels","gid":"22463","score":9.449999999999999289457264239899814128875732421875,"url":null,"place":4},{"tname":"Alaska","tid":"3","fname":"Kennedy ","lname":"Green","gid":"24503","score":9.425000000000000710542735760100185871124267578125,"url":null,"place":5},{"tname":"Cortland State","tid":"19","fname":"Lily","lname":"Szafranski","gid":"24438","score":9.4000000000000003552713678800500929355621337890625,"url":null,"place":6},{"tname":"Alaska","tid":"3","fname":"Mackenzie","lname":"Miller","gid":"24508","score":9.375,"url":null,"place":7},{"tname":"Cortland State","tid":"19","fname":"Sidney","lname":"McConnell","gid":"24893","score":9.375,"url":null,"place":7},{"tname":"Alaska","tid":"3","fname":"Isabelle","lname":"Fox","gid":"25140","score":9.3499999999999996447286321199499070644378662109375,"url":null,"place":9},{"tname":"Cortland State","tid":"19","fname":"Bailey","lname":"Gildemeyer","gid":"23783","score":9.0999999999999996447286321199499070644378662109375,"url":null,"place":10},{"tname":"Cortland State","tid":"19","fname":"Emma","lname":"Schulz","gid":"29768","score":8.9749999999999996447286321199499070644378662109375,"url":null,"place":11},{"tname":"Cortland State","tid":"19","fname":"McKenna","lname":"Passalacqua","gid":"23790","score":8.7249999999999996447286321199499070644378662109375,"url":null,"place":12}],"bars":[{"tname":"Alaska","tid":"3","fname":"Hope","lname":"Nelson","gid":"25141","score":9.75,"url":null,"place":1},{"tname":"Alaska","tid":"3","fname":"Isabelle","lname":"Fox","gid":"25140","score":9.5999999999999996447286321199499070644378662109375,"url":null,"place":2},{"tname":"Alaska","tid":"3","fname":"Mackenzie","lname":"Miller","gid":"24508","score":9.5999999999999996447286321199499070644378662109375,"url":null,"place":2},{"tname":"Alaska","tid":"3","fname":"Kierra ","lname":"Abraham","gid":"23967","score":9.1500000000000003552713678800500929355621337890625,"url":null,"place":4},{"tname":"Cortland State","tid":"19","fname":"Arianna","lname":"Turso","gid":"23795","score":9.050000000000000710542735760100185871124267578125,"url":null,"place":5},{"tname":"Cortland State","tid":"19","fname":"Lindsay","lname":"Riggs","gid":"24441","score":9.050000000000000710542735760100185871124267578125,"url":null,"place":5},{"tname":"Cortland State","tid":"19","fname":"Sidney","lname":"McConnell","gid":"24893","score":9,"url":null,"place":7},{"tname":"Cortland State","tid":"19","fname":"Mia ","lname":"Dimartino","gid":"24891","score":8.824999999999999289457264239899814128875732421875,"url":null,"place":8},{"tname":"Alaska","tid":"3","fname":"Kennedy ","lname":"Green","gid":"24503","score":8.6500000000000003552713678800500929355621337890625,"url":null,"place":9},{"tname":"Cortland State","tid":"19","fname":"Emily","lname":"Speciale","gid":"29776","score":8.625,"url":null,"place":10},{"tname":"Cortland State","tid":"19","fname":"Ashley","lname":"Scarantino","gid":"24890","score":7.5,"url":null,"place":11}],"beam":[{"tname":"Alaska","tid":"3","fname":"Hope","lname":"Nelson","gid":"25141","score":9.800000000000000710542735760100185871124267578125,"url":null,"place":1},{"tname":"Cortland State","tid":"19","fname":"Emma","lname":"Schulz","gid":"29768","score":9.800000000000000710542735760100185871124267578125,"url":null,"place":1},{"tname":"Alaska","tid":"3","fname":"Michaela","lname":"Phillips","gid":"25142","score":9.75,"url":null,"place":3},{"tname":"Alaska","tid":"3","fname":"Isabelle","lname":"Fox","gid":"25140","score":9.7249999999999996447286321199499070644378662109375,"url":null,"place":4},{"tname":"Cortland State","tid":"19","fname":"McKenna","lname":"Passalacqua","gid":"23790","score":9.675000000000000710542735760100185871124267578125,"url":null,"place":5},{"tname":"Alaska","tid":"3","fname":"Kaylin","lname":"Mancari","gid":"23970","score":9.625,"url":null,"place":6},{"tname":"Alaska","tid":"3","fname":"Mackenzie","lname":"Miller","gid":"24508","score":9.449999999999999289457264239899814128875732421875,"url":null,"place":7},{"tname":"Cortland State","tid":"19","fname":"Bailey","lname":"Gildemeyer","gid":"23783","score":9.449999999999999289457264239899814128875732421875,"url":null,"place":7},{"tname":"Alaska","tid":"3","fname":"Kendra","lname":"Daniels","gid":"22463","score":9.2750000000000003552713678800500929355621337890625,"url":null,"place":9},{"tname":"Cortland State","tid":"19","fname":"Julie","lname":"Giardina","gid":"29774","score":9.125,"url":null,"place":10},{"tname":"Cortland State","tid":"19","fname":"Arianna","lname":"Turso","gid":"23795","score":8.8499999999999996447286321199499070644378662109375,"url":null,"place":11},{"tname":"Cortland State","tid":"19","fname":"Genna","lname":"Orlik","gid":"24894","score":8.550000000000000710542735760100185871124267578125,"url":null,"place":12}],"floor":[{"tname":"Alaska","tid":"3","fname":"Isabelle","lname":"Fox","gid":"25140","score":9.699999999999999289457264239899814128875732421875,"url":null,"place":1},{"tname":"Alaska","tid":"3","fname":"Kaylin","lname":"Mancari","gid":"23970","score":9.675000000000000710542735760100185871124267578125,"url":null,"place":2},{"tname":"Alaska","tid":"3","fname":"Kennedy ","lname":"Green","gid":"24503","score":9.5,"url":null,"place":3},{"tname":"Cortland State","tid":"19","fname":"Emma","lname":"Schulz","gid":"29768","score":9.5,"url":null,"place":3},{"tname":"Cortland State","tid":"19","fname":"Arianna","lname":"Turso","gid":"23795","score":9.25,"url":null,"place":5},{"tname":"Cortland State","tid":"19","fname":"Samantha","lname":"Betz","gid":"29777","score":9.125,"url":null,"place":6},{"tname":"Alaska","tid":"3","fname":"Michaela","lname":"Phillips","gid":"25142","score":8.9000000000000003552713678800500929355621337890625,"url":null,"place":7},{"tname":"Alaska","tid":"3","fname":"Hope","lname":"Nelson","gid":"25141","score":8.675000000000000710542735760100185871124267578125,"url":null,"place":8},{"tname":"Cortland State","tid":"19","fname":"Julie","lname":"Giardina","gid":"29774","score":8.675000000000000710542735760100185871124267578125,"url":null,"place":8},{"tname":"Cortland State","tid":"19","fname":"Lily","lname":"Szafranski","gid":"24438","score":8.2750000000000003552713678800500929355621337890625,"url":null,"place":10},{"tname":"Cortland State","tid":"19","fname":"Rachel","lname":"Filipski","gid":"24437","score":7.4000000000000003552713678800500929355621337890625,"url":null,"place":11}],"aa":[{"tname":"Alaska","tid":"3","fname":"Isabelle","lname":"Fox","gid":"25140","score":38.375,"place":1}],"info":{"meet_desc":"","host":"Alaska","date":"Jan-12-2018","attendance":"477","live":false},"scoresheets":[]}