{"teams":[{"mid":"18143","tid":"47","tname":"Oklahoma","vault":"49.5250","bars":"49.5000","beam":"49.7500","floor":"49.7250","tscore":"198.5000","year":"2015","home":"H","lead":0},{"mid":"18057","tid":"22","tname":"Florida","vault":"49.5500","bars":"49.5500","beam":"49.5250","floor":"49.4750","tscore":"198.1000","year":"2015","home":"A","lead":0.40000000000000002220446049250313080847263336181640625}],"scores":[[{"gid":"22939","first_name":"Erica","last_name":"Brewer","vault":null,"bars":"9.8500","beam":"10.0000","floor":"9.9000","all_around":null,"team_name":"Oklahoma","team_id":"47","yr":"2015","vt_url":null,"ub_url":null,"bb_url":null,"fx_url":null},{"gid":"22941","first_name":"Chayse","last_name":"Capps","vault":"9.9000","bars":null,"beam":"9.9500","floor":"9.8250","all_around":null,"team_name":"Oklahoma","team_id":"47","yr":"2015","vt_url":null,"ub_url":null,"bb_url":null,"fx_url":null},{"gid":"22943","first_name":"Rebecca","last_name":"Clark","vault":null,"bars":"9.8750","beam":"9.9250","floor":null,"all_around":null,"team_name":"Oklahoma","team_id":"47","yr":"2015","vt_url":null,"ub_url":null,"bb_url":null,"fx_url":null},{"gid":"23715","first_name":"Brenna","last_name":"Dowell","vault":"9.8750","bars":"9.9500","beam":null,"floor":"9.9500","all_around":null,"team_name":"Oklahoma","team_id":"47","yr":"2015","vt_url":null,"ub_url":null,"bb_url":null,"fx_url":null},{"gid":"23714","first_name":"AJ","last_name":"Jackson","vault":"9.8500","bars":null,"beam":null,"floor":"9.9500","all_around":null,"team_name":"Oklahoma","team_id":"47","yr":"2015","vt_url":null,"ub_url":null,"bb_url":null,"fx_url":null},{"gid":"22949","first_name":"Keeley","last_name":"Kmieciak","vault":"9.9000","bars":"9.9000","beam":"9.9250","floor":null,"all_around":null,"team_name":"Oklahoma","team_id":"47","yr":"2015","vt_url":null,"ub_url":null,"bb_url":null,"fx_url":null},{"gid":"22950","first_name":"Kara","last_name":"Lovan","vault":"9.9000","bars":null,"beam":"9.9000","floor":"9.9250","all_around":null,"team_name":"Oklahoma","team_id":"47","yr":"2015","vt_url":null,"ub_url":null,"bb_url":null,"fx_url":null},{"gid":"22952","first_name":"Haley","last_name":"Scaman","vault":"9.9500","bars":"9.9000","beam":null,"floor":"10.0000","all_around":null,"team_name":"Oklahoma","team_id":"47","yr":"2015","vt_url":null,"ub_url":null,"bb_url":null,"fx_url":null},{"gid":"22953","first_name":"Haley","last_name":"Sorensen","vault":null,"bars":null,"beam":"9.9500","floor":null,"all_around":null,"team_name":"Oklahoma","team_id":"47","yr":"2015","vt_url":null,"ub_url":null,"bb_url":null,"fx_url":null},{"gid":"22954","first_name":"McKenzie","last_name":"Wofford","vault":null,"bars":"9.8750","beam":null,"floor":null,"all_around":null,"team_name":"Oklahoma","team_id":"47","yr":"2015","vt_url":null,"ub_url":null,"bb_url":null,"fx_url":null}],[{"gid":"22707","first_name":"Kennedy","last_name":"Baker","vault":"9.8750","bars":null,"beam":"9.8500","floor":"9.8500","all_around":null,"team_name":"Florida","team_id":"22","yr":"2015","vt_url":null,"ub_url":null,"bb_url":null,"fx_url":null},{"gid":"22708","first_name":"Claire","last_name":"Boyce","vault":null,"bars":null,"beam":null,"floor":"9.8750","all_around":null,"team_name":"Florida","team_id":"22","yr":"2015","vt_url":null,"ub_url":null,"bb_url":null,"fx_url":null},{"gid":"22709","first_name":"Bridgette","last_name":"Caquatto","vault":"9.8500","bars":"9.9000","beam":null,"floor":"9.9250","all_around":null,"team_name":"Florida","team_id":"22","yr":"2015","vt_url":null,"ub_url":null,"bb_url":null,"fx_url":null},{"gid":"22710","first_name":"Bianca","last_name":"Dancose-Giambattisto","vault":null,"bars":"9.8500","beam":null,"floor":null,"all_around":null,"team_name":"Florida","team_id":"22","yr":"2015","vt_url":null,"ub_url":null,"bb_url":null,"fx_url":null},{"gid":"22711","first_name":"Ericha","last_name":"Fassbender","vault":null,"bars":"9.7750","beam":"9.8750","floor":null,"all_around":null,"team_name":"Florida","team_id":"22","yr":"2015","vt_url":null,"ub_url":null,"bb_url":null,"fx_url":null},{"gid":"22713","first_name":"Kytra","last_name":"Hunter","vault":"9.9500","bars":"9.9000","beam":"9.9750","floor":"9.9250","all_around":"39.7500","team_name":"Florida","team_id":"22","yr":"2015","vt_url":null,"ub_url":null,"bb_url":null,"fx_url":null},{"gid":"22715","first_name":"Alex","last_name":"McMurtry","vault":"9.9750","bars":"9.9250","beam":"9.8750","floor":null,"all_around":null,"team_name":"Florida","team_id":"22","yr":"2015","vt_url":null,"ub_url":null,"bb_url":null,"fx_url":null},{"gid":"22717","first_name":"Bridget","last_name":"Sloan","vault":null,"bars":"9.9750","beam":"9.9250","floor":null,"all_around":null,"team_name":"Florida","team_id":"22","yr":"2015","vt_url":null,"ub_url":null,"bb_url":null,"fx_url":null},{"gid":"22718","first_name":"Rachel","last_name":"Spicer","vault":"9.8500","bars":null,"beam":"9.8750","floor":"9.8500","all_around":null,"team_name":"Florida","team_id":"22","yr":"2015","vt_url":null,"ub_url":null,"bb_url":null,"fx_url":null},{"gid":"22720","first_name":"Kiersten","last_name":"Wang","vault":"9.9000","bars":null,"beam":null,"floor":"9.9000","all_around":null,"team_name":"Florida","team_id":"22","yr":"2015","vt_url":null,"ub_url":null,"bb_url":null,"fx_url":null}]],"vault":[{"tname":"Florida","tid":"22","fname":"Alex","lname":"McMurtry","gid":"22715","score":9.9749999999999996447286321199499070644378662109375,"url":null,"place":1},{"tname":"Florida","tid":"22","fname":"Kytra","lname":"Hunter","gid":"22713","score":9.949999999999999289457264239899814128875732421875,"url":null,"place":2},{"tname":"Oklahoma","tid":"47","fname":"Haley","lname":"Scaman","gid":"22952","score":9.949999999999999289457264239899814128875732421875,"url":null,"place":2},{"tname":"Florida","tid":"22","fname":"Kiersten","lname":"Wang","gid":"22720","score":9.9000000000000003552713678800500929355621337890625,"url":null,"place":4},{"tname":"Oklahoma","tid":"47","fname":"Chayse","lname":"Capps","gid":"22941","score":9.9000000000000003552713678800500929355621337890625,"url":null,"place":4},{"tname":"Oklahoma","tid":"47","fname":"Kara","lname":"Lovan","gid":"22950","score":9.9000000000000003552713678800500929355621337890625,"url":null,"place":4},{"tname":"Oklahoma","tid":"47","fname":"Keeley","lname":"Kmieciak","gid":"22949","score":9.9000000000000003552713678800500929355621337890625,"url":null,"place":4},{"tname":"Florida","tid":"22","fname":"Kennedy","lname":"Baker","gid":"22707","score":9.875,"url":null,"place":8},{"tname":"Oklahoma","tid":"47","fname":"Brenna","lname":"Dowell","gid":"23715","score":9.875,"url":null,"place":8},{"tname":"Florida","tid":"22","fname":"Bridgette","lname":"Caquatto","gid":"22709","score":9.8499999999999996447286321199499070644378662109375,"url":null,"place":10},{"tname":"Florida","tid":"22","fname":"Rachel","lname":"Spicer","gid":"22718","score":9.8499999999999996447286321199499070644378662109375,"url":null,"place":10},{"tname":"Oklahoma","tid":"47","fname":"AJ","lname":"Jackson","gid":"23714","score":9.8499999999999996447286321199499070644378662109375,"url":null,"place":10}],"bars":[{"tname":"Florida","tid":"22","fname":"Bridget","lname":"Sloan","gid":"22717","score":9.9749999999999996447286321199499070644378662109375,"url":null,"place":1},{"tname":"Oklahoma","tid":"47","fname":"Brenna","lname":"Dowell","gid":"23715","score":9.949999999999999289457264239899814128875732421875,"url":null,"place":2},{"tname":"Florida","tid":"22","fname":"Alex","lname":"McMurtry","gid":"22715","score":9.925000000000000710542735760100185871124267578125,"url":null,"place":3},{"tname":"Florida","tid":"22","fname":"Bridgette","lname":"Caquatto","gid":"22709","score":9.9000000000000003552713678800500929355621337890625,"url":null,"place":4},{"tname":"Florida","tid":"22","fname":"Kytra","lname":"Hunter","gid":"22713","score":9.9000000000000003552713678800500929355621337890625,"url":null,"place":4},{"tname":"Oklahoma","tid":"47","fname":"Haley","lname":"Scaman","gid":"22952","score":9.9000000000000003552713678800500929355621337890625,"url":null,"place":4},{"tname":"Oklahoma","tid":"47","fname":"Keeley","lname":"Kmieciak","gid":"22949","score":9.9000000000000003552713678800500929355621337890625,"url":null,"place":4},{"tname":"Oklahoma","tid":"47","fname":"McKenzie","lname":"Wofford","gid":"22954","score":9.875,"url":null,"place":8},{"tname":"Oklahoma","tid":"47","fname":"Rebecca","lname":"Clark","gid":"22943","score":9.875,"url":null,"place":8},{"tname":"Florida","tid":"22","fname":"Bianca","lname":"Dancose-Giambattisto","gid":"22710","score":9.8499999999999996447286321199499070644378662109375,"url":null,"place":10},{"tname":"Oklahoma","tid":"47","fname":"Erica","lname":"Brewer","gid":"22939","score":9.8499999999999996447286321199499070644378662109375,"url":null,"place":10},{"tname":"Florida","tid":"22","fname":"Ericha","lname":"Fassbender","gid":"22711","score":9.7750000000000003552713678800500929355621337890625,"url":null,"place":12}],"beam":[{"tname":"Oklahoma","tid":"47","fname":"Erica","lname":"Brewer","gid":"22939","score":10,"url":null,"place":1},{"tname":"Florida","tid":"22","fname":"Kytra","lname":"Hunter","gid":"22713","score":9.9749999999999996447286321199499070644378662109375,"url":null,"place":2},{"tname":"Oklahoma","tid":"47","fname":"Chayse","lname":"Capps","gid":"22941","score":9.949999999999999289457264239899814128875732421875,"url":null,"place":3},{"tname":"Oklahoma","tid":"47","fname":"Haley","lname":"Sorensen","gid":"22953","score":9.949999999999999289457264239899814128875732421875,"url":null,"place":3},{"tname":"Florida","tid":"22","fname":"Bridget","lname":"Sloan","gid":"22717","score":9.925000000000000710542735760100185871124267578125,"url":null,"place":5},{"tname":"Oklahoma","tid":"47","fname":"Keeley","lname":"Kmieciak","gid":"22949","score":9.925000000000000710542735760100185871124267578125,"url":null,"place":5},{"tname":"Oklahoma","tid":"47","fname":"Rebecca","lname":"Clark","gid":"22943","score":9.925000000000000710542735760100185871124267578125,"url":null,"place":5},{"tname":"Oklahoma","tid":"47","fname":"Kara","lname":"Lovan","gid":"22950","score":9.9000000000000003552713678800500929355621337890625,"url":null,"place":8},{"tname":"Florida","tid":"22","fname":"Alex","lname":"McMurtry","gid":"22715","score":9.875,"url":null,"place":9},{"tname":"Florida","tid":"22","fname":"Ericha","lname":"Fassbender","gid":"22711","score":9.875,"url":null,"place":9},{"tname":"Florida","tid":"22","fname":"Rachel","lname":"Spicer","gid":"22718","score":9.875,"url":null,"place":9},{"tname":"Florida","tid":"22","fname":"Kennedy","lname":"Baker","gid":"22707","score":9.8499999999999996447286321199499070644378662109375,"url":null,"place":12}],"floor":[{"tname":"Oklahoma","tid":"47","fname":"Haley","lname":"Scaman","gid":"22952","score":10,"url":null,"place":1},{"tname":"Oklahoma","tid":"47","fname":"AJ","lname":"Jackson","gid":"23714","score":9.949999999999999289457264239899814128875732421875,"url":null,"place":2},{"tname":"Oklahoma","tid":"47","fname":"Brenna","lname":"Dowell","gid":"23715","score":9.949999999999999289457264239899814128875732421875,"url":null,"place":2},{"tname":"Florida","tid":"22","fname":"Bridgette","lname":"Caquatto","gid":"22709","score":9.925000000000000710542735760100185871124267578125,"url":null,"place":4},{"tname":"Florida","tid":"22","fname":"Kytra","lname":"Hunter","gid":"22713","score":9.925000000000000710542735760100185871124267578125,"url":null,"place":4},{"tname":"Oklahoma","tid":"47","fname":"Kara","lname":"Lovan","gid":"22950","score":9.925000000000000710542735760100185871124267578125,"url":null,"place":4},{"tname":"Florida","tid":"22","fname":"Kiersten","lname":"Wang","gid":"22720","score":9.9000000000000003552713678800500929355621337890625,"url":null,"place":7},{"tname":"Oklahoma","tid":"47","fname":"Erica","lname":"Brewer","gid":"22939","score":9.9000000000000003552713678800500929355621337890625,"url":null,"place":7},{"tname":"Florida","tid":"22","fname":"Claire","lname":"Boyce","gid":"22708","score":9.875,"url":null,"place":9},{"tname":"Florida","tid":"22","fname":"Kennedy","lname":"Baker","gid":"22707","score":9.8499999999999996447286321199499070644378662109375,"url":null,"place":10},{"tname":"Florida","tid":"22","fname":"Rachel","lname":"Spicer","gid":"22718","score":9.8499999999999996447286321199499070644378662109375,"url":null,"place":10},{"tname":"Oklahoma","tid":"47","fname":"Chayse","lname":"Capps","gid":"22941","score":9.824999999999999289457264239899814128875732421875,"url":null,"place":12}],"aa":[{"tname":"Florida","tid":"22","fname":"Kytra","lname":"Hunter","gid":"22713","score":39.75,"place":1}],"info":{"meet_desc":"","host":"Oklahoma","date":"Mar-06-2015","attendance":"4138","live":false},"scoresheets":[]}