{"teams":[{"mid":"19286","tid":"32","tname":"Kent State","vault":"48.6250","bars":"48.7750","beam":"48.8750","floor":"49.0500","tscore":"195.3250","year":"2016","home":"A","lead":0},{"mid":"19833","tid":"17","tname":"Central Michigan","vault":"48.8500","bars":"48.5000","beam":"48.6500","floor":"48.5500","tscore":"194.5500","year":"2016","home":"H","lead":0.77500000000000002220446049250313080847263336181640625}],"scores":[[{"gid":"22786","first_name":"Nicolle","last_name":"Eastman","vault":"9.7250","bars":null,"beam":"9.6750","floor":"9.8000","all_around":null,"team_name":"Kent State","team_id":"32","yr":"2016","vt_url":null,"ub_url":null,"bb_url":null,"fx_url":null},{"gid":"22787","first_name":"Milena","last_name":"Fabry","vault":null,"bars":null,"beam":"9.7250","floor":null,"all_around":null,"team_name":"Kent State","team_id":"32","yr":"2016","vt_url":null,"ub_url":null,"bb_url":null,"fx_url":null},{"gid":"22788","first_name":"Samantha","last_name":"Gordon","vault":null,"bars":null,"beam":null,"floor":"9.7750","all_around":null,"team_name":"Kent State","team_id":"32","yr":"2016","vt_url":null,"ub_url":null,"bb_url":null,"fx_url":null},{"gid":"22789","first_name":"Jordan","last_name":"Hardison","vault":"9.7250","bars":null,"beam":null,"floor":"9.8500","all_around":null,"team_name":"Kent State","team_id":"32","yr":"2016","vt_url":null,"ub_url":null,"bb_url":null,"fx_url":null},{"gid":"22793","first_name":"Skyelee","last_name":"Lamano","vault":"9.7250","bars":"9.7500","beam":null,"floor":"9.6250","all_around":null,"team_name":"Kent State","team_id":"32","yr":"2016","vt_url":null,"ub_url":null,"bb_url":null,"fx_url":null},{"gid":"24070","first_name":"Sarah","last_name":"Lippowitsch","vault":null,"bars":"9.7250","beam":null,"floor":null,"all_around":null,"team_name":"Kent State","team_id":"32","yr":"2016","vt_url":null,"ub_url":null,"bb_url":null,"fx_url":null},{"gid":"22795","first_name":"Ali","last_name":"Marrero","vault":null,"bars":"9.2500","beam":"9.7750","floor":null,"all_around":null,"team_name":"Kent State","team_id":"32","yr":"2016","vt_url":null,"ub_url":null,"bb_url":null,"fx_url":null},{"gid":"24064","first_name":"Kennedy","last_name":"Plude","vault":"9.6750","bars":null,"beam":"9.7750","floor":null,"all_around":null,"team_name":"Kent State","team_id":"32","yr":"2016","vt_url":null,"ub_url":null,"bb_url":null,"fx_url":null},{"gid":"22799","first_name":"Michaela","last_name":"Romito","vault":"9.7000","bars":"9.8250","beam":null,"floor":"9.7250","all_around":null,"team_name":"Kent State","team_id":"32","yr":"2016","vt_url":null,"ub_url":null,"bb_url":null,"fx_url":null},{"gid":"22801","first_name":"Rachel","last_name":"Stypinski","vault":null,"bars":"9.7750","beam":"9.8250","floor":"9.9000","all_around":null,"team_name":"Kent State","team_id":"32","yr":"2016","vt_url":null,"ub_url":null,"bb_url":null,"fx_url":null},{"gid":"22802","first_name":"Brooke","last_name":"Timko","vault":"9.7500","bars":"9.7000","beam":"9.7750","floor":null,"all_around":null,"team_name":"Kent State","team_id":"32","yr":"2016","vt_url":null,"ub_url":null,"bb_url":null,"fx_url":null}],[{"gid":"23278","first_name":"Taylor","last_name":"Bolender","vault":"9.7250","bars":"9.1750","beam":"9.7500","floor":"9.9000","all_around":"38.5500","team_name":"Central Michigan","team_id":"17","yr":"2016","vt_url":null,"ub_url":null,"bb_url":null,"fx_url":null},{"gid":"23280","first_name":"Rachel","last_name":"Carr","vault":"9.7750","bars":"9.7000","beam":null,"floor":null,"all_around":null,"team_name":"Central Michigan","team_id":"17","yr":"2016","vt_url":null,"ub_url":null,"bb_url":null,"fx_url":null},{"gid":"23281","first_name":"Jordan","last_name":"Charrette","vault":null,"bars":null,"beam":"9.7250","floor":null,"all_around":null,"team_name":"Central Michigan","team_id":"17","yr":"2016","vt_url":null,"ub_url":null,"bb_url":null,"fx_url":null},{"gid":"23282","first_name":"Katy","last_name":"Clements","vault":"9.7250","bars":null,"beam":"9.7500","floor":null,"all_around":null,"team_name":"Central Michigan","team_id":"17","yr":"2016","vt_url":null,"ub_url":null,"bb_url":null,"fx_url":null},{"gid":"23285","first_name":"Caroline","last_name":"Fitzpatrick","vault":null,"bars":null,"beam":"9.1250","floor":null,"all_around":null,"team_name":"Central Michigan","team_id":"17","yr":"2016","vt_url":null,"ub_url":null,"bb_url":null,"fx_url":null},{"gid":"23288","first_name":"Macey","last_name":"Hilliker","vault":null,"bars":null,"beam":"9.6500","floor":"9.8500","all_around":null,"team_name":"Central Michigan","team_id":"17","yr":"2016","vt_url":null,"ub_url":null,"bb_url":null,"fx_url":null},{"gid":"24352","first_name":"Kasey","last_name":"Janowicz","vault":"9.8500","bars":"9.8750","beam":"9.7750","floor":"9.6500","all_around":"39.1500","team_name":"Central Michigan","team_id":"17","yr":"2016","vt_url":null,"ub_url":null,"bb_url":null,"fx_url":null},{"gid":"23289","first_name":"Bryttany","last_name":"Kaplan","vault":null,"bars":"9.8500","beam":null,"floor":null,"all_around":null,"team_name":"Central Michigan","team_id":"17","yr":"2016","vt_url":null,"ub_url":null,"bb_url":null,"fx_url":null},{"gid":"23290","first_name":"Megan","last_name":"Lamphere","vault":null,"bars":"9.9000","beam":null,"floor":null,"all_around":null,"team_name":"Central Michigan","team_id":"17","yr":"2016","vt_url":null,"ub_url":null,"bb_url":null,"fx_url":null},{"gid":"24354","first_name":"Kailey","last_name":"Miller","vault":null,"bars":null,"beam":null,"floor":"9.0250","all_around":null,"team_name":"Central Michigan","team_id":"17","yr":"2016","vt_url":null,"ub_url":null,"bb_url":null,"fx_url":null},{"gid":"24446","first_name":"Gianna","last_name":"Plaksa","vault":null,"bars":null,"beam":null,"floor":"9.8000","all_around":null,"team_name":"Central Michigan","team_id":"17","yr":"2016","vt_url":null,"ub_url":null,"bb_url":null,"fx_url":null},{"gid":"23295","first_name":"Jodie","last_name":"Plescow","vault":"9.7750","bars":null,"beam":null,"floor":null,"all_around":null,"team_name":"Central Michigan","team_id":"17","yr":"2016","vt_url":null,"ub_url":null,"bb_url":null,"fx_url":null},{"gid":"23298","first_name":"Karlee","last_name":"Teet","vault":"9.4500","bars":"8.6000","beam":null,"floor":null,"all_around":null,"team_name":"Central Michigan","team_id":"17","yr":"2016","vt_url":null,"ub_url":null,"bb_url":null,"fx_url":null},{"gid":"24356","first_name":"Abbie Rose","last_name":"Zoeller","vault":null,"bars":null,"beam":null,"floor":"9.3500","all_around":null,"team_name":"Central Michigan","team_id":"17","yr":"2016","vt_url":null,"ub_url":null,"bb_url":null,"fx_url":null}]],"vault":[{"tname":"Central Michigan","tid":"17","fname":"Kasey","lname":"Janowicz","gid":"24352","score":9.8499999999999996447286321199499070644378662109375,"url":null,"place":1},{"tname":"Central Michigan","tid":"17","fname":"Jodie","lname":"Plescow","gid":"23295","score":9.7750000000000003552713678800500929355621337890625,"url":null,"place":2},{"tname":"Central Michigan","tid":"17","fname":"Rachel","lname":"Carr","gid":"23280","score":9.7750000000000003552713678800500929355621337890625,"url":null,"place":2},{"tname":"Kent State","tid":"32","fname":"Brooke","lname":"Timko","gid":"22802","score":9.75,"url":null,"place":4},{"tname":"Central Michigan","tid":"17","fname":"Katy","lname":"Clements","gid":"23282","score":9.7249999999999996447286321199499070644378662109375,"url":null,"place":5},{"tname":"Central Michigan","tid":"17","fname":"Taylor","lname":"Bolender","gid":"23278","score":9.7249999999999996447286321199499070644378662109375,"url":null,"place":5},{"tname":"Kent State","tid":"32","fname":"Jordan","lname":"Hardison","gid":"22789","score":9.7249999999999996447286321199499070644378662109375,"url":null,"place":5},{"tname":"Kent State","tid":"32","fname":"Nicolle","lname":"Eastman","gid":"22786","score":9.7249999999999996447286321199499070644378662109375,"url":null,"place":5},{"tname":"Kent State","tid":"32","fname":"Skyelee","lname":"Lamano","gid":"22793","score":9.7249999999999996447286321199499070644378662109375,"url":null,"place":5},{"tname":"Kent State","tid":"32","fname":"Michaela","lname":"Romito","gid":"22799","score":9.699999999999999289457264239899814128875732421875,"url":null,"place":10},{"tname":"Kent State","tid":"32","fname":"Kennedy","lname":"Plude","gid":"24064","score":9.675000000000000710542735760100185871124267578125,"url":null,"place":11},{"tname":"Central Michigan","tid":"17","fname":"Karlee","lname":"Teet","gid":"23298","score":9.449999999999999289457264239899814128875732421875,"url":null,"place":12}],"bars":[{"tname":"Central Michigan","tid":"17","fname":"Megan","lname":"Lamphere","gid":"23290","score":9.9000000000000003552713678800500929355621337890625,"url":null,"place":1},{"tname":"Central Michigan","tid":"17","fname":"Kasey","lname":"Janowicz","gid":"24352","score":9.875,"url":null,"place":2},{"tname":"Central Michigan","tid":"17","fname":"Bryttany","lname":"Kaplan","gid":"23289","score":9.8499999999999996447286321199499070644378662109375,"url":null,"place":3},{"tname":"Kent State","tid":"32","fname":"Michaela","lname":"Romito","gid":"22799","score":9.824999999999999289457264239899814128875732421875,"url":null,"place":4},{"tname":"Kent State","tid":"32","fname":"Rachel","lname":"Stypinski","gid":"22801","score":9.7750000000000003552713678800500929355621337890625,"url":null,"place":5},{"tname":"Kent State","tid":"32","fname":"Skyelee","lname":"Lamano","gid":"22793","score":9.75,"url":null,"place":6},{"tname":"Kent State","tid":"32","fname":"Sarah","lname":"Lippowitsch","gid":"24070","score":9.7249999999999996447286321199499070644378662109375,"url":null,"place":7},{"tname":"Central Michigan","tid":"17","fname":"Rachel","lname":"Carr","gid":"23280","score":9.699999999999999289457264239899814128875732421875,"url":null,"place":8},{"tname":"Kent State","tid":"32","fname":"Brooke","lname":"Timko","gid":"22802","score":9.699999999999999289457264239899814128875732421875,"url":null,"place":8},{"tname":"Kent State","tid":"32","fname":"Ali","lname":"Marrero","gid":"22795","score":9.25,"url":null,"place":10},{"tname":"Central Michigan","tid":"17","fname":"Taylor","lname":"Bolender","gid":"23278","score":9.175000000000000710542735760100185871124267578125,"url":null,"place":11},{"tname":"Central Michigan","tid":"17","fname":"Karlee","lname":"Teet","gid":"23298","score":8.5999999999999996447286321199499070644378662109375,"url":null,"place":12}],"beam":[{"tname":"Kent State","tid":"32","fname":"Rachel","lname":"Stypinski","gid":"22801","score":9.824999999999999289457264239899814128875732421875,"url":null,"place":1},{"tname":"Central Michigan","tid":"17","fname":"Kasey","lname":"Janowicz","gid":"24352","score":9.7750000000000003552713678800500929355621337890625,"url":null,"place":2},{"tname":"Kent State","tid":"32","fname":"Ali","lname":"Marrero","gid":"22795","score":9.7750000000000003552713678800500929355621337890625,"url":null,"place":2},{"tname":"Kent State","tid":"32","fname":"Brooke","lname":"Timko","gid":"22802","score":9.7750000000000003552713678800500929355621337890625,"url":null,"place":2},{"tname":"Kent State","tid":"32","fname":"Kennedy","lname":"Plude","gid":"24064","score":9.7750000000000003552713678800500929355621337890625,"url":null,"place":2},{"tname":"Central Michigan","tid":"17","fname":"Katy","lname":"Clements","gid":"23282","score":9.75,"url":null,"place":6},{"tname":"Central Michigan","tid":"17","fname":"Taylor","lname":"Bolender","gid":"23278","score":9.75,"url":null,"place":6},{"tname":"Central Michigan","tid":"17","fname":"Jordan","lname":"Charrette","gid":"23281","score":9.7249999999999996447286321199499070644378662109375,"url":null,"place":8},{"tname":"Kent State","tid":"32","fname":"Milena","lname":"Fabry","gid":"22787","score":9.7249999999999996447286321199499070644378662109375,"url":null,"place":8},{"tname":"Kent State","tid":"32","fname":"Nicolle","lname":"Eastman","gid":"22786","score":9.675000000000000710542735760100185871124267578125,"url":null,"place":10},{"tname":"Central Michigan","tid":"17","fname":"Macey","lname":"Hilliker","gid":"23288","score":9.6500000000000003552713678800500929355621337890625,"url":null,"place":11},{"tname":"Central Michigan","tid":"17","fname":"Caroline","lname":"Fitzpatrick","gid":"23285","score":9.125,"url":null,"place":12}],"floor":[{"tname":"Central Michigan","tid":"17","fname":"Taylor","lname":"Bolender","gid":"23278","score":9.9000000000000003552713678800500929355621337890625,"url":null,"place":1},{"tname":"Kent State","tid":"32","fname":"Rachel","lname":"Stypinski","gid":"22801","score":9.9000000000000003552713678800500929355621337890625,"url":null,"place":1},{"tname":"Central Michigan","tid":"17","fname":"Macey","lname":"Hilliker","gid":"23288","score":9.8499999999999996447286321199499070644378662109375,"url":null,"place":3},{"tname":"Kent State","tid":"32","fname":"Jordan","lname":"Hardison","gid":"22789","score":9.8499999999999996447286321199499070644378662109375,"url":null,"place":3},{"tname":"Central Michigan","tid":"17","fname":"Gianna","lname":"Plaksa","gid":"24446","score":9.800000000000000710542735760100185871124267578125,"url":null,"place":5},{"tname":"Kent State","tid":"32","fname":"Nicolle","lname":"Eastman","gid":"22786","score":9.800000000000000710542735760100185871124267578125,"url":null,"place":5},{"tname":"Kent State","tid":"32","fname":"Samantha","lname":"Gordon","gid":"22788","score":9.7750000000000003552713678800500929355621337890625,"url":null,"place":7},{"tname":"Kent State","tid":"32","fname":"Michaela","lname":"Romito","gid":"22799","score":9.7249999999999996447286321199499070644378662109375,"url":null,"place":8},{"tname":"Central Michigan","tid":"17","fname":"Kasey","lname":"Janowicz","gid":"24352","score":9.6500000000000003552713678800500929355621337890625,"url":null,"place":9},{"tname":"Kent State","tid":"32","fname":"Skyelee","lname":"Lamano","gid":"22793","score":9.625,"url":null,"place":10},{"tname":"Central Michigan","tid":"17","fname":"Abbie Rose","lname":"Zoeller","gid":"24356","score":9.3499999999999996447286321199499070644378662109375,"url":null,"place":11},{"tname":"Central Michigan","tid":"17","fname":"Kailey","lname":"Miller","gid":"24354","score":9.0250000000000003552713678800500929355621337890625,"url":null,"place":12}],"aa":[{"tname":"Central Michigan","tid":"17","fname":"Kasey","lname":"Janowicz","gid":"24352","score":39.14999999999999857891452847979962825775146484375,"place":1},{"tname":"Central Michigan","tid":"17","fname":"Taylor","lname":"Bolender","gid":"23278","score":38.5499999999999971578290569595992565155029296875,"place":2}],"info":{"meet_desc":"","host":"Central Michigan","date":"Feb-28-2016","attendance":"634","live":false},"scoresheets":[]}